tdp_matomo/__init__.py
tdp_matomo/config.json
tdp_matomo-8.0.0.dist-info/LICENSE
tdp_matomo-8.0.0.dist-info/METADATA
tdp_matomo-8.0.0.dist-info/WHEEL
tdp_matomo-8.0.0.dist-info/entry_points.txt
tdp_matomo-8.0.0.dist-info/top_level.txt
tdp_matomo-8.0.0.dist-info/RECORD
