Metadata-Version: 2.1
Name: tdp-matomo
Version: 8.0.0
Summary: DEPRECATED: Matomo tracking for TDP applications
Home-page: https://www.datavisyn.io
Author: datavisyn GmbH
Author-email: contact@datavisyn.io
License: BSD-3-Clause
Platform: UNKNOWN
Classifier: Intended Audience :: Developers
Classifier: Operating System :: OS Independent
Classifier: License :: OSI Approved :: BSD License
Classifier: Programming Language :: Python
Classifier: Programming Language :: Python :: 3.7
License-File: LICENSE
Requires-Dist: tdp-core (<13.0.0,>=12.1.2)
